flacfixer/__init__.py
flacfixer/cli.py
flacfixer/fixer.py
flacfixer/recursive_executor.py
flacfixer/util.py
flacfixer-2.0.dist-info/LICENSE
flacfixer-2.0.dist-info/METADATA
flacfixer-2.0.dist-info/WHEEL
flacfixer-2.0.dist-info/entry_points.txt
flacfixer-2.0.dist-info/top_level.txt
flacfixer-2.0.dist-info/RECORD
