Metadata-Version: 2.2
Name: flacfixer
Version: 2.0
Summary: Rename music files and album directories automatically
License: GPLv3
Project-URL: Homepage, https://sr.ht:~rensoliemans/flacfixer
Project-URL: Repository, https://git.sr.ht:~rensoliemans/flacfixer
Project-URL: Issues, https://lists.sr.ht/~rensoliemans/flacfixer
Project-URL: CI, https://builds.sr.ht/~rensoliemans/flacfixer
Classifier: License :: OSI Approved :: GNU General Public License (GPL)
Requires-Python: >=3.9
License-File: LICENSE
Requires-Dist: mutagen~=1.46.0
Provides-Extra: dev
Requires-Dist: black~=22.6.0; extra == "dev"
Requires-Dist: ruff~=0.0.235; extra == "dev"
Requires-Dist: mypy~=0.971; extra == "dev"
Requires-Dist: pre-commit~=3.1.0; extra == "dev"
Provides-Extra: build
Requires-Dist: setuptools; extra == "build"
Requires-Dist: build; extra == "build"
Requires-Dist: twine; extra == "build"
